itershap/__init__.py
itershap/itershap.py
itershap-0.1.1.dist-info/LICENSE.txt
itershap-0.1.1.dist-info/METADATA
itershap-0.1.1.dist-info/WHEEL
itershap-0.1.1.dist-info/RECORD
