Metadata-Version: 2.1
Name: itershap
Version: 0.1.1
Summary: Iterative feature selection method using SHAP values
Home-page: https://github.com/FrankvanMourik/IterSHAP
License: MIT
Keywords: SHAP,Feature Selection,Explainable AI,XAI,Small datasets
Author: Frank van Mourik
Author-email: f.g.vanmourik@student.utwente.nl
Requires-Python: >=3.10,<3.11
Classifier: License :: OSI Approved :: MIT License
Classifier: Programming Language :: Python :: 3
Classifier: Programming Language :: Python :: 3.10
Requires-Dist: numpy
Requires-Dist: pandas
Requires-Dist: scikit-learn
Requires-Dist: shap
Requires-Dist: xgboost
Project-URL: Repository, https://github.com/FrankvanMourik/IterSHAP
